tk_gui_tools/__init__.py
tk_gui_tools/main.py
tk_gui_tools/manage_widget.py
tk_gui_tools/settings.py
tk_gui_tools/template_manager.py
tk_gui_tools/command_gui/__init__.py
tk_gui_tools/command_gui/command.py
tk_gui_tools/command_gui/keyboard.py
tk_gui_tools/command_gui/mouse.py
tk_gui_tools/template/__init__.py
tk_gui_tools/template/base.py
tk_gui_tools/template/dashboard.py
tk_gui_tools/test/__init__.py
tk_gui_tools/test/test_command.py
tk_gui_tools/test/test_global.py
tk_gui_tools/test/test_template.py
tk_gui_tools/test/test_widget/__init__.py
tk_gui_tools/test/test_widget/test_button.py
tk_gui_tools/test/test_widget/test_menu.py
tk_gui_tools/test/test_widget/test_rectangle.py
tk_gui_tools/test/test_widget/test_round.py
tk_gui_tools/test/test_widget/test_text.py
tk_gui_tools/tool/__init__.py
tk_gui_tools/tool/scroolbar.py
tk_gui_tools/widget/__init__.py
tk_gui_tools/widget/button.py
tk_gui_tools/widget/menu.py
tk_gui_tools/widget/rectangle.py
tk_gui_tools/widget/round.py
tk_gui_tools/widget/text.py
guitool-0.1.3.dist-info/LICENCE.txt
guitool-0.1.3.dist-info/METADATA
guitool-0.1.3.dist-info/WHEEL
guitool-0.1.3.dist-info/top_level.txt
guitool-0.1.3.dist-info/RECORD
