Metadata-Version: 2.1
Name: guitool
Version: 0.1.3
Summary: Quickly create a user interface based on tkinter's canvas
Home-page: https://github.com/Walrick/gui_tool
Author: Jeremy COMBES
Author-email: jeremy.combes0902@gmail.com
License: MIT License
Platform: UNKNOWN
License-File: LICENCE.txt
